{"tags":{"http:\/\/api.twitter.com\/1\/users\/show.json?user_id=16676422":"6","http:\/\/api.twitter.com\/1\/users\/show.json?user_id=19528648":"2","http:\/\/api.twitter.com\/1\/users\/show.json?user_id=17645454":"1","http:\/\/api.twitter.com\/1\/users\/show.json?user_id=14305608":"1","http:\/\/api.twitter.com\/1\/users\/show.json?user_id=15242920":"1","http:\/\/api.twitter.com\/1\/users\/show.json?user_id=21345179":"1","http:\/\/api.twitter.com\/1\/users\/show.json?user_id=52483406":"1","http:\/\/api.twitter.com\/1\/users\/show.json?user_id=11388132":"1","http:\/\/api.twitter.com\/1\/users\/show.json?user_id=29655018":"1","http:\/\/api.twitter.com\/1\/users\/show.json?user_id=14435486":"1","http:\/\/api.twitter.com\/1\/users\/show.json?user_id=5983942":"1","http:\/\/api.twitter.com\/1\/users\/show.json?user_id=16065829":"1","http:\/\/api.twitter.com\/1\/users\/show.json?user_id=17189369":"1","http:\/\/api.twitter.com\/1\/users\/show.json?user_id=61974746":"1","http:\/\/api.twitter.com\/1\/users\/show.json?user_id=26032668":"1","http:\/\/api.twitter.com\/1\/users\/show.json?user_id=15439395":"1","http:\/\/api.twitter.com\/1\/users\/show.json?user_id=64693923":"1","http:\/\/api.twitter.com\/1\/users\/show.json?user_id=19238793":"1","http:\/\/api.twitter.com\/1\/users\/show.json?user_id=2204721":"1","http:\/\/api.twitter.com\/1\/users\/show.json?user_id=15937226":"1","http:\/\/api.twitter.com\/1\/users\/show.json?user_id=25668519":"1","http:\/\/api.twitter.com\/1\/users\/show.json?user_id=17250680":"1","http:\/\/api.twitter.com\/1\/users\/show.json?user_id=15382400":"1","http:\/\/api.twitter.com\/1\/users\/show.json?user_id=11129862":"1","http:\/\/api.twitter.com\/1\/users\/show.json?user_id=18972865":"1","http:\/\/api.twitter.com\/1\/users\/show.json?user_id=16576302":"1","http:\/\/api.twitter.com\/1\/users\/show.json?user_id=7690032":"1","http:\/\/api.twitter.com\/1\/users\/show.json?user_id=14451677":"1","http:\/\/api.twitter.com\/1\/users\/show.json?user_id=15008728":"1","http:\/\/api.twitter.com\/1\/users\/show.json?user_id=6148272":"1","http:\/\/api.twitter.com\/1\/users\/show.json?user_id=16646918":"1","http:\/\/api.twitter.com\/1\/users\/show.json?user_id=10653682":"1","http:\/\/api.twitter.com\/1\/users\/show.json?user_id=15144620":"1","http:\/\/api.twitter.com\/1\/users\/show.json?user_id=11576052":"1","http:\/\/api.twitter.com\/1\/users\/show.json?user_id=1495591":"1"},"friends":[],"mentions":{"http:\/\/api.twitter.com\/1\/users\/show.json?user_id=16676422":"65","http:\/\/api.twitter.com\/1\/users\/show.json?user_id=91079515":"2","http:\/\/api.twitter.com\/1\/users\/show.json?user_id=21827584":"2","http:\/\/api.twitter.com\/1\/users\/show.json?user_id=5472852":"1","http:\/\/api.twitter.com\/1\/users\/show.json?user_id=764365":"1","http:\/\/api.twitter.com\/1\/users\/show.json?user_id=19354607":"1","http:\/\/api.twitter.com\/1\/users\/show.json?user_id=34853":"1","http:\/\/api.twitter.com\/1\/users\/show.json?user_id=1285451":"1","http:\/\/api.twitter.com\/1\/users\/show.json?user_id=7170942":"1","http:\/\/api.twitter.com\/1\/users\/show.json?user_id=27864916":"1"}}