{"tags":{"http:\/\/api.twitter.com\/1\/users\/show.json?user_id=16025085":"99","http:\/\/api.twitter.com\/1\/users\/show.json?user_id=21686948":"10","http:\/\/api.twitter.com\/1\/users\/show.json?user_id=17665358":"8","http:\/\/api.twitter.com\/1\/users\/show.json?user_id=27141700":"7","http:\/\/api.twitter.com\/1\/users\/show.json?user_id=5824502":"7","http:\/\/api.twitter.com\/1\/users\/show.json?user_id=1495591":"7","http:\/\/api.twitter.com\/1\/users\/show.json?user_id=59065473":"7","http:\/\/api.twitter.com\/1\/users\/show.json?user_id=19902178":"7","http:\/\/api.twitter.com\/1\/users\/show.json?user_id=6287562":"7","http:\/\/api.twitter.com\/1\/users\/show.json?user_id=18918827":"7","http:\/\/api.twitter.com\/1\/users\/show.json?user_id=73705954":"6","http:\/\/api.twitter.com\/1\/users\/show.json?user_id=17917075":"6","http:\/\/api.twitter.com\/1\/users\/show.json?user_id=3231671":"6","http:\/\/api.twitter.com\/1\/users\/show.json?user_id=1558651":"6","http:\/\/api.twitter.com\/1\/users\/show.json?user_id=14112331":"6","http:\/\/api.twitter.com\/1\/users\/show.json?user_id=20803360":"6","http:\/\/api.twitter.com\/1\/users\/show.json?user_id=16065829":"6","http:\/\/api.twitter.com\/1\/users\/show.json?user_id=10653682":"6","http:\/\/api.twitter.com\/1\/users\/show.json?user_id=49254438":"6","http:\/\/api.twitter.com\/1\/users\/show.json?user_id=15271509":"6","http:\/\/api.twitter.com\/1\/users\/show.json?user_id=77841866":"6","http:\/\/api.twitter.com\/1\/users\/show.json?user_id=26270899":"6","http:\/\/api.twitter.com\/1\/users\/show.json?user_id=14858710":"6","http:\/\/api.twitter.com\/1\/users\/show.json?user_id=27197606":"6","http:\/\/api.twitter.com\/1\/users\/show.json?user_id=14300444":"6","http:\/\/api.twitter.com\/1\/users\/show.json?user_id=32844572":"6","http:\/\/api.twitter.com\/1\/users\/show.json?user_id=53977749":"6","http:\/\/api.twitter.com\/1\/users\/show.json?user_id=9204972":"6","http:\/\/api.twitter.com\/1\/users\/show.json?user_id=14838292":"6","http:\/\/api.twitter.com\/1\/users\/show.json?user_id=72581281":"6","http:\/\/api.twitter.com\/1\/users\/show.json?user_id=51894745":"6","http:\/\/api.twitter.com\/1\/users\/show.json?user_id=9316452":"5","http:\/\/api.twitter.com\/1\/users\/show.json?user_id=28299655":"5","http:\/\/api.twitter.com\/1\/users\/show.json?user_id=57279302":"5","http:\/\/api.twitter.com\/1\/users\/show.json?user_id=14989462":"5"},"friends":[],"mentions":{"http:\/\/api.twitter.com\/1\/users\/show.json?user_id=16025085":"99","http:\/\/api.twitter.com\/1\/users\/show.json?user_id=84133944":"13","http:\/\/api.twitter.com\/1\/users\/show.json?user_id=21500149":"4","http:\/\/api.twitter.com\/1\/users\/show.json?user_id=10821":"3","http:\/\/api.twitter.com\/1\/users\/show.json?user_id=9070682":"2","http:\/\/api.twitter.com\/1\/users\/show.json?user_id=9126002":"2","http:\/\/api.twitter.com\/1\/users\/show.json?user_id=14207200":"1","http:\/\/api.twitter.com\/1\/users\/show.json?user_id=14677806":"1","http:\/\/api.twitter.com\/1\/users\/show.json?user_id=18123568":"1","http:\/\/api.twitter.com\/1\/users\/show.json?user_id=5848122":"1","http:\/\/api.twitter.com\/1\/users\/show.json?user_id=1282151":"1","http:\/\/api.twitter.com\/1\/users\/show.json?user_id=16830577":"1","http:\/\/api.twitter.com\/1\/users\/show.json?user_id=17406425":"1","http:\/\/api.twitter.com\/1\/users\/show.json?user_id=15677958":"1","http:\/\/api.twitter.com\/1\/users\/show.json?user_id=14838292":"1","http:\/\/api.twitter.com\/1\/users\/show.json?user_id=106840674":"1","http:\/\/api.twitter.com\/1\/users\/show.json?user_id=14290420":"1","http:\/\/api.twitter.com\/1\/users\/show.json?user_id=1712831":"1","http:\/\/api.twitter.com\/1\/users\/show.json?user_id=3231671":"1","http:\/\/api.twitter.com\/1\/users\/show.json?user_id=68332899":"1","http:\/\/api.twitter.com\/1\/users\/show.json?user_id=144605504":"1","http:\/\/api.twitter.com\/1\/users\/show.json?user_id=16250713":"1","http:\/\/api.twitter.com\/1\/users\/show.json?user_id=2204721":"1","http:\/\/api.twitter.com\/1\/users\/show.json?user_id=19763720":"1","http:\/\/api.twitter.com\/1\/users\/show.json?user_id=14388339":"1","http:\/\/api.twitter.com\/1\/users\/show.json?user_id=1855871":"1","http:\/\/api.twitter.com\/1\/users\/show.json?user_id=17042405":"1","http:\/\/api.twitter.com\/1\/users\/show.json?user_id=15603409":"1","http:\/\/api.twitter.com\/1\/users\/show.json?user_id=16489324":"1","http:\/\/api.twitter.com\/1\/users\/show.json?user_id=15746084":"1","http:\/\/api.twitter.com\/1\/users\/show.json?user_id=4519121":"1","http:\/\/api.twitter.com\/1\/users\/show.json?user_id=13567":"1","http:\/\/api.twitter.com\/1\/users\/show.json?user_id=812103":"1","http:\/\/api.twitter.com\/1\/users\/show.json?user_id=17270693":"1","http:\/\/api.twitter.com\/1\/users\/show.json?user_id=8139122":"1"}}