{"tags":{"http:\/\/api.twitter.com\/1\/users\/show.json?user_id=91581610":"28","http:\/\/api.twitter.com\/1\/users\/show.json?user_id=138372303":"12","http:\/\/api.twitter.com\/1\/users\/show.json?user_id=143129711":"10","http:\/\/api.twitter.com\/1\/users\/show.json?user_id=24583612":"6","http:\/\/api.twitter.com\/1\/users\/show.json?user_id=20871212":"6","http:\/\/api.twitter.com\/1\/users\/show.json?user_id=52509224":"5","http:\/\/api.twitter.com\/1\/users\/show.json?user_id=69755555":"5","http:\/\/api.twitter.com\/1\/users\/show.json?user_id=37717959":"5","http:\/\/api.twitter.com\/1\/users\/show.json?user_id=15286924":"4","http:\/\/api.twitter.com\/1\/users\/show.json?user_id=62318528":"4","http:\/\/api.twitter.com\/1\/users\/show.json?user_id=21686948":"3","http:\/\/api.twitter.com\/1\/users\/show.json?user_id=16468998":"3","http:\/\/api.twitter.com\/1\/users\/show.json?user_id=23984573":"2","http:\/\/api.twitter.com\/1\/users\/show.json?user_id=5439642":"2","http:\/\/api.twitter.com\/1\/users\/show.json?user_id=64688392":"2","http:\/\/api.twitter.com\/1\/users\/show.json?user_id=2383781":"2","http:\/\/api.twitter.com\/1\/users\/show.json?user_id=13092722":"2","http:\/\/api.twitter.com\/1\/users\/show.json?user_id=10534182":"2","http:\/\/api.twitter.com\/1\/users\/show.json?user_id=18123568":"2","http:\/\/api.twitter.com\/1\/users\/show.json?user_id=68332899":"2","http:\/\/api.twitter.com\/1\/users\/show.json?user_id=15138336":"1","http:\/\/api.twitter.com\/1\/users\/show.json?user_id=35761106":"1","http:\/\/api.twitter.com\/1\/users\/show.json?user_id=154096311":"1","http:\/\/api.twitter.com\/1\/users\/show.json?user_id=9204972":"1","http:\/\/api.twitter.com\/1\/users\/show.json?user_id=5845762":"1","http:\/\/api.twitter.com\/1\/users\/show.json?user_id=36853217":"1","http:\/\/api.twitter.com\/1\/users\/show.json?user_id=15367824":"1","http:\/\/api.twitter.com\/1\/users\/show.json?user_id=807515":"1","http:\/\/api.twitter.com\/1\/users\/show.json?user_id=57273038":"1","http:\/\/api.twitter.com\/1\/users\/show.json?user_id=17841627":"1","http:\/\/api.twitter.com\/1\/users\/show.json?user_id=29402792":"1","http:\/\/api.twitter.com\/1\/users\/show.json?user_id=15045590":"1","http:\/\/api.twitter.com\/1\/users\/show.json?user_id=33452924":"1","http:\/\/api.twitter.com\/1\/users\/show.json?user_id=10211232":"1","http:\/\/api.twitter.com\/1\/users\/show.json?user_id=6167532":"1"},"friends":[],"mentions":{"http:\/\/api.twitter.com\/1\/users\/show.json?user_id=91581610":"62","http:\/\/api.twitter.com\/1\/users\/show.json?user_id=81550369":"2","http:\/\/api.twitter.com\/1\/users\/show.json?user_id=6885202":"2","http:\/\/api.twitter.com\/1\/users\/show.json?user_id=40580924":"2","http:\/\/api.twitter.com\/1\/users\/show.json?user_id=16144104":"2","http:\/\/api.twitter.com\/1\/users\/show.json?user_id=7696252":"1","http:\/\/api.twitter.com\/1\/users\/show.json?user_id=18368680":"1","http:\/\/api.twitter.com\/1\/users\/show.json?user_id=14300444":"1","http:\/\/api.twitter.com\/1\/users\/show.json?user_id=96016951":"1","http:\/\/api.twitter.com\/1\/users\/show.json?user_id=15405165":"1","http:\/\/api.twitter.com\/1\/users\/show.json?user_id=38639438":"1","http:\/\/api.twitter.com\/1\/users\/show.json?user_id=44850087":"1","http:\/\/api.twitter.com\/1\/users\/show.json?user_id=9939992":"1","http:\/\/api.twitter.com\/1\/users\/show.json?user_id=20871212":"1","http:\/\/api.twitter.com\/1\/users\/show.json?user_id=1368561":"1","http:\/\/api.twitter.com\/1\/users\/show.json?user_id=9334352":"1","http:\/\/api.twitter.com\/1\/users\/show.json?user_id=7083182":"1","http:\/\/api.twitter.com\/1\/users\/show.json?user_id=40112219":"1","http:\/\/api.twitter.com\/1\/users\/show.json?user_id=64688392":"1","http:\/\/api.twitter.com\/1\/users\/show.json?user_id=15533183":"1","http:\/\/api.twitter.com\/1\/users\/show.json?user_id=16250713":"1","http:\/\/api.twitter.com\/1\/users\/show.json?user_id=15008728":"1","http:\/\/api.twitter.com\/1\/users\/show.json?user_id=15904103":"1","http:\/\/api.twitter.com\/1\/users\/show.json?user_id=22638914":"1","http:\/\/api.twitter.com\/1\/users\/show.json?user_id=6467932":"1","http:\/\/api.twitter.com\/1\/users\/show.json?user_id=164023294":"1","http:\/\/api.twitter.com\/1\/users\/show.json?user_id=55197432":"1","http:\/\/api.twitter.com\/1\/users\/show.json?user_id=5437052":"1","http:\/\/api.twitter.com\/1\/users\/show.json?user_id=9126002":"1","http:\/\/api.twitter.com\/1\/users\/show.json?user_id=15286924":"1","http:\/\/api.twitter.com\/1\/users\/show.json?user_id=1417761":"1","http:\/\/api.twitter.com\/1\/users\/show.json?user_id=105811013":"1","http:\/\/api.twitter.com\/1\/users\/show.json?user_id=15183686":"1","http:\/\/api.twitter.com\/1\/users\/show.json?user_id=15645104":"1","http:\/\/api.twitter.com\/1\/users\/show.json?user_id=807515":"1"}}